{"html_attributions": [], "result": {"address_components": [{"long_name": "Antonienstra\u00dfe", "short_name": "Antonienstra\u00dfe", "types": ["route"]}, {"long_name": "Bezirk Reinickendorf", "short_name": "Bezirk Reinickendorf", "types": ["sublocality_level_1", "sublocality", "political"]}, {"long_name": "Berlin", "short_name": "Berlin", "types": ["locality", "political"]}, {"long_name": "Berlin", "short_name": "Berlin", "types": ["administrative_area_level_1", "political"]}, {"long_name": "Germany", "short_name": "DE", "types": ["country", "political"]}, {"long_name": "13403", "short_name": "13403", "types": ["postal_code"]}], "adr_address": "<span class=\"street-address\">Antonienstra\u00dfe</span>, <span class=\"postal-code\">13403</span> <span class=\"locality\">Berlin</span>, <span class=\"country-name\">Germany</span>", "business_status": "OPERATIONAL", "formatted_address": "Antonienstra\u00dfe, 13403 Berlin, Germany", "geometry": {"location": {"lat": 52.57738759999999, "lng": 13.3144839}, "viewport": {"northeast": {"lat": 52.5786939302915, "lng": 13.3159434802915}, "southwest": {"lat": 52.5759959697085, "lng": 13.3132455197085}}}, "icon": "https://maps.gstatic.com/mapfiles/place_api/icons/v1/png_71/restaurant-71.png", "name": "Berlin Burger Box", "photos": [{"height": 3024, "html_attributions": ["<a href=\"https://maps.google.com/maps/contrib/117516030572761806659\">Quang Dang</a>"], "photo_reference": "ATtYBwKrrAQsck54WQCJy2GDoO8vsUMdmli7siZD9hCTEw-d2JMd-nNRrnXa0gK_Lr4tSwaSxiLqy3Wr9zi8AyUzblFWi1n2S5Dz1eKroRfDGduvFWbBu8QXvG8TBIQ7JU_SWvDV6Tk30sPhIseakkLQbGxvA0SFHl05mXsuOUUJruYZRA-C", "width": 4032}], "place_id": "ChIJ3wZTW2NTqEcR2Qd63_HgHVQ", "plus_code": {"compound_code": "H8G7+XQ Berlin, Germany", "global_code": "9F4MH8G7+XQ"}, "reference": "ChIJ3wZTW2NTqEcR2Qd63_HgHVQ", "types": ["restaurant", "food", "point_of_interest", "establishment"], "url": "https://maps.google.com/?cid=6061248002951612377", "utc_offset": 60, "vicinity": "Antonienstra\u00dfe, Berlin", "website": "https://www.berlin-burger-box.de/"}, "status": "OK"}